[{"id": "en:arctic-sea", "name": "Arctic sea"}, {"id": "en:asia", "name": "Asia"}, {"id": "en:atlantic-ocean", "name": "Atlantic Ocean"}, {"id": "en:europe", "name": "Europe"}, {"id": "en:indian-ocean", "name": "Indian Ocean"}, {"id": "en:kosovo", "name": "Kosovo"}, {"id": "en:non-european-union", "name": "Non European Union"}, {"id": "en:pacific-ocean", "name": "Pacific Ocean"}, {"id": "en:palestinian-territories", "name": "Palestinian territories"}, {"id": "en:iceland", "name": "アイスランド"}, {"id": "en:ireland", "name": "アイルランド"}, {"id": "en:azerbaijan", "name": "アゼルバイジャン"}, {"id": "en:afghanistan", "name": "アフガニスタン"}, {"id": "en:africa", "name": "アフリカ"}, {"id": "en:united-states", "name": "アメリカ合衆国"}, {"id": "en:american-samoa", "name": "アメリカ領サモア"}, {"id": "en:virgin-islands-of-the-united-states", "name": "アメリカ領ヴァージン諸島"}, {"id": "en:united-arab-emirates", "name": "アラブ首長国連邦"}, {"id": "en:algeria", "name": "アルジェリア"}, {"id": "en:argentina", "name": "アルゼンチン"}, {"id": "en:aruba", "name": "アルバ"}, {"id": "en:albania", "name": "アルバニア"}, {"id": "en:armenia", "name": "アルメニア"}, {"id": "en:anguilla", "name": "アンギラ"}, {"id": "en:angola", "name": "アンゴラ"}, {"id": "en:antigua-and-barbuda", "name": "アンティグア・バーブーダ"}, {"id": "en:andorra", "name": "アンドラ"}, {"id": "en:yemen", "name": "イエメン"}, {"id": "en:united-kingdom", "name": "イギリス"}, {"id": "en:british-indian-ocean-territory", "name": "イギリス領インド洋地域"}, {"id": "en:british-virgin-islands", "name": "イギリス領ヴァージン諸島"}, {"id": "en:israel", "name": "イスラエル"}, {"id": "en:italy", "name": "イタリア"}, {"id": "en:iraq", "name": "イラク"}, {"id": "en:iran", "name": "イラン"}, {"id": "en:india", "name": "インド"}, {"id": "en:indonesia", "name": "インドネシア"}, {"id": "en:wallis-and-futuna", "name": "ウォリス・フツナ"}, {"id": "en:uganda", "name": "ウガンダ"}, {"id": "en:ukraine", "name": "ウクライナ"}, {"id": "en:uzbekistan", "name": "ウズベキスタン"}, {"id": "en:uruguay", "name": "ウルグアイ"}, {"id": "en:ecuador", "name": "エクアドル"}, {"id": "en:egypt", "name": "エジプト"}, {"id": "en:estonia", "name": "エストニア"}, {"id": "en:ethiopia", "name": "エチオピア"}, {"id": "en:eritrea", "name": "エリトリア"}, {"id": "en:el-salvador", "name": "エルサルバドル"}, {"id": "en:oman", "name": "オマーン"}, {"id": "en:netherlands", "name": "オランダ"}, {"id": "en:australia", "name": "オーストラリア"}, {"id": "en:austria", "name": "オーストリア"}, {"id": "en:aland-islands", "name": "オーランド諸島"}, {"id": "en:kazakhstan", "name": "カザフスタン"}, {"id": "en:qatar", "name": "カタール"}, {"id": "en:canada", "name": "カナダ"}, {"id": "en:cameroon", "name": "カメルーン"}, {"id": "en:cambodia", "name": "カンボジア"}, {"id": "en:cape-verde", "name": "カーボベルデ"}, {"id": "en:guyana", "name": "ガイアナ"}, {"id": "en:gabon", "name": "ガボン"}, {"id": "en:gambia", "name": "ガンビア"}, {"id": "en:ghana", "name": "ガーナ"}, {"id": "en:guernsey", "name": "ガーンジー"}, {"id": "en:cyprus", "name": "キプロス"}, {"id": "en:curacao", "name": "キュラソー島"}, {"id": "en:cuba", "name": "キューバ"}, {"id": "en:kiribati", "name": "キリバス"}, {"id": "en:kyrgyzstan", "name": "キルギス"}, {"id": "en:guinea", "name": "ギニア"}, {"id": "en:guinea-bissau", "name": "ギニアビサウ"}, {"id": "en:greece", "name": "ギリシャ"}, {"id": "en:kuwait", "name": "クウェート"}, {"id": "en:cook-islands", "name": "クック諸島"}, {"id": "en:christmas-island", "name": "クリスマス島"}, {"id": "en:croatia", "name": "クロアチア"}, {"id": "en:guatemala", "name": "グアテマラ"}, {"id": "en:guadeloupe", "name": "グアドループ"}, {"id": "en:guam", "name": "グアム"}, {"id": "en:greenland", "name": "グリーンランド"}, {"id": "en:georgia", "name": "グルジア"}, {"id": "en:grenada", "name": "グレナダ"}, {"id": "en:cayman-islands", "name": "ケイマン諸島"}, {"id": "en:kenya", "name": "ケニア"}, {"id": "en:cocos-keeling-islands", "name": "ココス諸島"}, {"id": "en:costa-rica", "name": "コスタリカ"}, {"id": "en:comoros", "name": "コモロ"}, {"id": "en:colombia", "name": "コロンビア"}, {"id": "en:republic-of-the-congo", "name": "コンゴ共和国"}, {"id": "en:democratic-republic-of-the-congo", "name": "コンゴ民主共和国"}, {"id": "en:cote-d-ivoire", "name": "コートジボワール"}, {"id": "en:saudi-arabia", "name": "サウジアラビア"}, {"id": "en:south-georgia-and-the-south-sandwich-islands", "name": "サウスジョージア・サウスサンドウィッチ諸島"}, {"id": "en:samoa", "name": "サモア"}, {"id": "en:sao-tome-and-principe", "name": "サントメ・プリンシペ"}, {"id": "en:saint-pierre-and-miquelon", "name": "サンピエール島・ミクロン島"}, {"id": "en:san-marino", "name": "サンマリノ"}, {"id": "en:saint-barthelemy", "name": "サン・バルテルミー島"}, {"id": "en:saint-martin", "name": "サン・マルタン"}, {"id": "en:zambia", "name": "ザンビア"}, {"id": "en:sierra-leone", "name": "シエラレオネ"}, {"id": "en:syria", "name": "シリア"}, {"id": "en:singapore", "name": "シンガポール"}, {"id": "en:sint-maarten", "name": "シント・マールテン"}, {"id": "en:djibouti", "name": "ジブチ"}, {"id": "en:gibraltar", "name": "ジブラルタル"}, {"id": "en:jamaica", "name": "ジャマイカ"}, {"id": "en:jersey", "name": "ジャージー"}, {"id": "en:zimbabwe", "name": "ジンバブエ"}, {"id": "en:switzerland", "name": "スイス"}, {"id": "en:sweden", "name": "スウェーデン"}, {"id": "en:spain", "name": "スペイン"}, {"id": "en:suriname", "name": "スリナム"}, {"id": "en:sri-lanka", "name": "スリランカ"}, {"id": "en:slovakia", "name": "スロバキア"}, {"id": "en:slovenia", "name": "スロベニア"}, {"id": "en:swaziland", "name": "スワジランド"}, {"id": "en:svalbard-and-jan-mayen", "name": "スヴァールバル諸島およびヤンマイエン島"}, {"id": "en:sudan", "name": "スーダン"}, {"id": "en:senegal", "name": "セネガル"}, {"id": "en:serbia", "name": "セルビア"}, {"id": "en:saint-kitts-and-nevis", "name": "セントクリストファー・ネイビス"}, {"id": "en:saint-vincent-and-the-grenadines", "name": "セントビンセント・グレナディーン"}, {"id": "en:saint-helena", "name": "セントヘレナ・アセンションおよびトリスタンダクーニャ"}, {"id": "en:saint-lucia", "name": "セントルシア"}, {"id": "en:seychelles", "name": "セーシェル"}, {"id": "en:somalia", "name": "ソマリア"}, {"id": "en:solomon-islands", "name": "ソロモン諸島"}, {"id": "en:thailand", "name": "タイ王国"}, {"id": "en:tajikistan", "name": "タジキスタン"}, {"id": "en:tanzania", "name": "タンザニア"}, {"id": "en:turks-and-caicos-islands", "name": "タークス・カイコス諸島"}, {"id": "en:czech-republic", "name": "チェコ"}, {"id": "en:chad", "name": "チャド"}, {"id": "en:tunisia", "name": "チュニジア"}, {"id": "en:chile", "name": "チリ"}, {"id": "en:tuvalu", "name": "ツバル"}, {"id": "en:denmark", "name": "デンマーク"}, {"id": "en:tokelau", "name": "トケラウ"}, {"id": "en:trinidad-and-tobago", "name": "トリニダード・トバゴ"}, {"id": "en:turkmenistan", "name": "トルクメニスタン"}, {"id": "en:turkey", "name": "トルコ"}, {"id": "en:tonga", "name": "トンガ"}, {"id": "en:togo", "name": "トーゴ"}, {"id": "en:germany", "name": "ドイツ"}, {"id": "en:dominican-republic", "name": "ドミニカ共和国"}, {"id": "en:dominica", "name": "ドミニカ国"}, {"id": "en:nigeria", "name": "ナイジェリア"}, {"id": "en:nauru", "name": "ナウル"}, {"id": "en:namibia", "name": "ナミビア"}, {"id": "en:niue", "name": "ニウエ"}, {"id": "en:nicaragua", "name": "ニカラグア"}, {"id": "en:niger", "name": "ニジェール"}, {"id": "en:new-caledonia", "name": "ニューカレドニア"}, {"id": "en:new-zealand", "name": "ニュージーランド"}, {"id": "en:nepal", "name": "ネパール"}, {"id": "en:norway", "name": "ノルウェー"}, {"id": "en:norfolk-island", "name": "ノーフォーク島"}, {"id": "en:haiti", "name": "ハイチ"}, {"id": "en:hungary", "name": "ハンガリー"}, {"id": "en:heard-island-and-mcdonald-islands", "name": "ハード島とマクドナルド諸島"}, {"id": "en:vatican-city", "name": "バチカン"}, {"id": "en:vanuatu", "name": "バヌアツ"}, {"id": "en:the-bahamas", "name": "バハマ"}, {"id": "en:bermuda", "name": "バミューダ諸島"}, {"id": "en:barbados", "name": "バルバドス"}, {"id": "en:bangladesh", "name": "バングラデシュ"}, {"id": "en:bahrain", "name": "バーレーン"}, {"id": "en:pakistan", "name": "パキスタン"}, {"id": "en:panama", "name": "パナマ"}, {"id": "en:papua-new-guinea", "name": "パプアニューギニア"}, {"id": "en:palau", "name": "パラオ"}, {"id": "en:paraguay", "name": "パラグアイ"}, {"id": "en:state-of-palestine", "name": "パレスチナ国"}, {"id": "en:pitcairn", "name": "ピトケアン諸島"}, {"id": "en:fiji", "name": "フィジー"}, {"id": "en:philippines", "name": "フィリピン"}, {"id": "en:finland", "name": "フィンランド"}, {"id": "en:faroe-islands", "name": "フェロー諸島"}, {"id": "en:falkland-islands", "name": "フォークランド諸島"}, {"id": "en:france", "name": "フランス"}, {"id": "en:french-guiana", "name": "フランス領ギアナ"}, {"id": "en:french-polynesia", "name": "フランス領ポリネシア"}, {"id": "en:french-southern-and-antarctic-lands", "name": "フランス領南方・南極地域"}, {"id": "en:brazil", "name": "ブラジル"}, {"id": "en:bulgaria", "name": "ブルガリア"}, {"id": "en:burkina-faso", "name": "ブルキナファソ"}, {"id": "en:brunei", "name": "ブルネイ"}, {"id": "en:burundi", "name": "ブルンジ"}, {"id": "en:bhutan", "name": "ブータン"}, {"id": "en:bouvet-island", "name": "ブーベ島"}, {"id": "en:puerto-rico", "name": "プエルトリコ"}, {"id": "en:vietnam", "name": "ベトナム"}, {"id": "en:benin", "name": "ベナン"}, {"id": "en:venezuela", "name": "ベネズエラ"}, {"id": "en:belarus", "name": "ベラルーシ"}, {"id": "en:belize", "name": "ベリーズ"}, {"id": "en:belgium", "name": "ベルギー"}, {"id": "en:peru", "name": "ペルー"}, {"id": "en:honduras", "name": "ホンジュラス"}, {"id": "en:bosnia-and-herzegovina", "name": "ボスニア・ヘルツェゴビナ"}, {"id": "en:botswana", "name": "ボツワナ"}, {"id": "en:caribbean-netherlands", "name": "ボネール、シント・ユースタティウスおよびサバ"}, {"id": "en:bolivia", "name": "ボリビア"}, {"id": "en:portugal", "name": "ポルトガル"}, {"id": "en:poland", "name": "ポーランド"}, {"id": "en:macau", "name": "マカオ"}, {"id": "en:madagascar", "name": "マダガスカル"}, {"id": "en:mayotte", "name": "マヨット"}, {"id": "en:malawi", "name": "マラウイ"}, {"id": "en:mali", "name": "マリ共和国"}, {"id": "en:malta", "name": "マルタ"}, {"id": "en:martinique", "name": "マルティニーク"}, {"id": "en:malaysia", "name": "マレーシア"}, {"id": "en:isle-of-man", "name": "マン島"}, {"id": "en:marshall-islands", "name": "マーシャル諸島"}, {"id": "en:federated-states-of-micronesia", "name": "ミクロネシア"}, {"id": "en:myanmar", "name": "ミャンマー"}, {"id": "en:mexico", "name": "メキシコ"}, {"id": "en:mozambique", "name": "モザンビーク"}, {"id": "en:monaco", "name": "モナコ"}, {"id": "en:maldives", "name": "モルディブ"}, {"id": "en:moldova", "name": "モルドバ"}, {"id": "en:morocco", "name": "モロッコ"}, {"id": "en:mongolia", "name": "モンゴル国"}, {"id": "en:montenegro", "name": "モンテネグロ"}, {"id": "en:montserrat", "name": "モントセラト"}, {"id": "en:mauritius", "name": "モーリシャス"}, {"id": "en:mauritania", "name": "モーリタニア"}, {"id": "en:yugoslavia", "name": "ユーゴスラビア"}, {"id": "en:jordan", "name": "ヨルダン"}, {"id": "en:laos", "name": "ラオス"}, {"id": "en:latvia", "name": "ラトビア"}, {"id": "en:lithuania", "name": "リトアニア"}, {"id": "en:liechtenstein", "name": "リヒテンシュタイン"}, {"id": "en:libya", "name": "リビア"}, {"id": "en:liberia", "name": "リベリア"}, {"id": "en:luxembourg", "name": "ルクセンブルク"}, {"id": "en:rwanda", "name": "ルワンダ"}, {"id": "en:romania", "name": "ルーマニア"}, {"id": "en:lesotho", "name": "レソト"}, {"id": "en:lebanon", "name": "レバノン"}, {"id": "en:reunion", "name": "レユニオン"}, {"id": "en:russia", "name": "ロシア"}, {"id": "en:unknown", "name": "不明"}, {"id": "en:world", "name": "世界"}, {"id": "en:central-african-republic", "name": "中央アフリカ共和国"}, {"id": "en:china", "name": "中華人民共和国"}, {"id": "en:taiwan", "name": "中華民国"}, {"id": "en:north-macedonia", "name": "北マケドニア"}, {"id": "en:northern-mariana-islands", "name": "北マリアナ諸島"}, {"id": "en:south-africa", "name": "南アフリカ共和国"}, {"id": "en:south-america", "name": "南アメリカ"}, {"id": "en:south-sudan", "name": "南スーダン"}, {"id": "en:antarctic", "name": "南極"}, {"id": "en:united-states-minor-outlying-islands", "name": "合衆国領有小離島"}, {"id": "en:south-korea", "name": "大韓民国"}, {"id": "en:japan", "name": "日本"}, {"id": "en:north-korea", "name": "朝鮮民主主義人民共和国"}, {"id": "en:timor-leste", "name": "東ティモール"}, {"id": "en:european-union", "name": "欧州連合"}, {"id": "en:western-sahara", "name": "西サハラ"}, {"id": "en:equatorial-guinea", "name": "赤道ギニア"}, {"id": "en:hong-kong", "name": "香港"}]