[{"id": "en:afghanistan", "name": "Afganistan", "country_code_2": "AF"}, {"id": "en:albania", "name": "Albanía", "country_code_2": "AL"}, {"id": "en:algeria", "name": "Alsír", "country_code_2": "DZ"}, {"id": "en:china", "name": "Alþýðulýðveldið Kína", "country_code_2": "CN"}, {"id": "en:andorra", "name": "Andorra", "country_code_2": "AD"}, {"id": "en:anguilla", "name": "Angvilla", "country_code_2": "AI"}, {"id": "en:angola", "name": "Angóla", "country_code_2": "AO"}, {"id": "en:antarctic", "name": "Antarctic", "country_code_2": "AQ"}, {"id": "en:antigua-and-barbuda", "name": "Antígva og Barbúda", "country_code_2": "AG"}, {"id": "en:argentina", "name": "Argentína", "country_code_2": "AR"}, {"id": "en:armenia", "name": "Armenía", "country_code_2": "AM"}, {"id": "en:aruba", "name": "Arúba", "country_code_2": "AW"}, {"id": "en:azerbaijan", "name": "Aserbaídsjan", "country_code_2": "AZ"}, {"id": "en:democratic-republic-of-the-congo", "name": "Austur-Kongó", "country_code_2": "CD"}, {"id": "en:timor-leste", "name": "Austur-Tímor", "country_code_2": "TL"}, {"id": "en:austria", "name": "Austurríki", "country_code_2": "AT"}, {"id": "en:the-bahamas", "name": "Bahamaeyjar", "country_code_2": "BS"}, {"id": "en:united-states", "name": "Bandaríkin", "country_code_2": "US"}, {"id": "en:american-samoa", "name": "Bandaríska Samóa", "country_code_2": "AS"}, {"id": "en:virgin-islands-of-the-united-states", "name": "Bandarísku Jómfrúaeyjar", "country_code_2": "VI"}, {"id": "en:bangladesh", "name": "Bangladess", "country_code_2": "BD"}, {"id": "en:barbados", "name": "Barbados", "country_code_2": "BB"}, {"id": "en:bahrain", "name": "Barein", "country_code_2": "BH"}, {"id": "en:belgium", "name": "Belgía", "country_code_2": "BE"}, {"id": "en:belize", "name": "Belís", "country_code_2": "BZ"}, {"id": "en:benin", "name": "Benín", "country_code_2": "BJ"}, {"id": "en:bermuda", "name": "Bermúda", "country_code_2": "BM"}, {"id": "en:bosnia-and-herzegovina", "name": "Bosnía og Hersegóvína", "country_code_2": "BA"}, {"id": "en:botswana", "name": "Botsvana", "country_code_2": "BW"}, {"id": "en:bouvet-island", "name": "Bouveteyja", "country_code_2": "BV"}, {"id": "en:brazil", "name": "Brasilía", "country_code_2": "BR"}, {"id": "en:british-indian-ocean-territory", "name": "Bresku Indlandshafseyjar", "country_code_2": "IO"}, {"id": "en:british-virgin-islands", "name": "Bresku Jómfrúaeyjar", "country_code_2": "VG"}, {"id": "en:united-kingdom", "name": "Bretland", "country_code_2": "UK"}, {"id": "en:brunei", "name": "Brúnei", "country_code_2": "BN"}, {"id": "en:bolivia", "name": "Bólivía", "country_code_2": "BO"}, {"id": "en:bulgaria", "name": "Búlgaría", "country_code_2": "BG"}, {"id": "en:burkina-faso", "name": "Búrkína Fasó", "country_code_2": "BF"}, {"id": "en:myanmar", "name": "Búrma", "country_code_2": "MM"}, {"id": "en:burundi", "name": "Búrúndí", "country_code_2": "BI"}, {"id": "en:bhutan", "name": "Bútan", "country_code_2": "BT"}, {"id": "en:caribbean-netherlands", "name": "Caribbean Netherlands", "country_code_2": "BQ"}, {"id": "en:cayman-islands", "name": "Caymaneyjar", "country_code_2": "KY"}, {"id": "en:cook-islands", "name": "Cooks-eyjar", "country_code_2": "CK"}, {"id": "en:curacao", "name": "Curaçao", "country_code_2": "CW"}, {"id": "en:denmark", "name": "Danmörk", "country_code_2": "DK"}, {"id": "en:djibouti", "name": "Djíbútí", "country_code_2": "DJ"}, {"id": "en:dominica", "name": "Dóminíka", "country_code_2": "DM"}, {"id": "en:dominican-republic", "name": "Dóminíska lýðveldið", "country_code_2": "DO"}, {"id": "en:egypt", "name": "Egyptaland", "country_code_2": "EG"}, {"id": "en:estonia", "name": "Eistland", "country_code_2": "EE"}, {"id": "en:ecuador", "name": "Ekvador", "country_code_2": "EC"}, {"id": "en:el-salvador", "name": "El Salvador", "country_code_2": "SV"}, {"id": "en:eritrea", "name": "Erítrea", "country_code_2": "ER"}, {"id": "en:ethiopia", "name": "Eþíópía", "country_code_2": "ET"}, {"id": "en:falkland-islands", "name": "Falklandseyjar", "country_code_2": "FK"}, {"id": "en:philippines", "name": "Filippseyjar", "country_code_2": "PH"}, {"id": "en:finland", "name": "Finnland", "country_code_2": "FI"}, {"id": "en:france", "name": "Frakkland", "country_code_2": "FR"}, {"id": "en:french-guiana", "name": "Franska Gvæjana", "country_code_2": "GF"}, {"id": "en:french-polynesia", "name": "Franska Pólýnesía", "country_code_2": "PF"}, {"id": "en:french-southern-and-antarctic-lands", "name": "Frönsku suðlægu landsvæðin", "country_code_2": "TF"}, {"id": "en:faroe-islands", "name": "Færeyjar", "country_code_2": "FO"}, {"id": "en:fiji", "name": "Fídjieyjar", "country_code_2": "FJ"}, {"id": "en:cote-d-ivoire", "name": "Fílabeinsströndin", "country_code_2": "CI"}, {"id": "en:gabon", "name": "Gabon", "country_code_2": "GA"}, {"id": "en:gambia", "name": "Gambía", "country_code_2": "GM"}, {"id": "en:ghana", "name": "Gana", "country_code_2": "GH"}, {"id": "en:georgia", "name": "Georgía", "country_code_2": "GE"}, {"id": "en:grenada", "name": "Grenada", "country_code_2": "GD"}, {"id": "en:greece", "name": "Grikkland", "country_code_2": "GR"}, {"id": "en:cape-verde", "name": "Grænhöfðaeyjar", "country_code_2": "CV"}, {"id": "en:greenland", "name": "Grænland", "country_code_2": "GL"}, {"id": "en:guernsey", "name": "Guernsey", "country_code_2": "GG"}, {"id": "en:guadeloupe", "name": "Gvadelúpeyjar", "country_code_2": "GP"}, {"id": "en:guam", "name": "Gvam", "country_code_2": "GU"}, {"id": "en:guatemala", "name": "Gvatemala", "country_code_2": "GT"}, {"id": "en:guyana", "name": "Gvæjana", "country_code_2": "GY"}, {"id": "en:gibraltar", "name": "Gíbraltar", "country_code_2": "GI"}, {"id": "en:guinea", "name": "Gínea", "country_code_2": "GN"}, {"id": "en:guinea-bissau", "name": "Gínea-Bissá", "country_code_2": "GW"}, {"id": "en:haiti", "name": "Haítí", "country_code_2": "HT"}, {"id": "en:heard-island-and-mcdonald-islands", "name": "Heard og McDonaldseyjar", "country_code_2": "HM"}, {"id": "en:netherlands", "name": "Holland", "country_code_2": "NL"}, {"id": "en:honduras", "name": "Hondúras", "country_code_2": "HN"}, {"id": "en:hong-kong", "name": "Hong Kong", "country_code_2": "HK"}, {"id": "en:belarus", "name": "Hvíta-Rússland", "country_code_2": "BY"}, {"id": "en:india", "name": "Indland", "country_code_2": "IN"}, {"id": "en:indonesia", "name": "Indónesía", "country_code_2": "ID"}, {"id": "en:jamaica", "name": "Jamaíka", "country_code_2": "JM"}, {"id": "en:japan", "name": "Japan", "country_code_2": "JP"}, {"id": "en:yemen", "name": "Jemen", "country_code_2": "YE"}, {"id": "en:jersey", "name": "Jersey", "country_code_2": "JE"}, {"id": "en:christmas-island", "name": "Jólaeyja", "country_code_2": "CX"}, {"id": "en:jordan", "name": "Jórdanía", "country_code_2": "JO"}, {"id": "en:yugoslavia", "name": "Júgóslavía", "country_code_2": "YU"}, {"id": "en:cambodia", "name": "Kambódía", "country_code_2": "KH"}, {"id": "en:cameroon", "name": "Kamerún", "country_code_2": "CM"}, {"id": "en:canada", "name": "Kanada", "country_code_2": "CA"}, {"id": "en:kazakhstan", "name": "Kasakstan", "country_code_2": "KZ"}, {"id": "en:qatar", "name": "Katar", "country_code_2": "QA"}, {"id": "en:kenya", "name": "Kenía", "country_code_2": "KE"}, {"id": "en:kyrgyzstan", "name": "Kirgisistan", "country_code_2": "KG"}, {"id": "en:kosovo", "name": "Kosovo", "country_code_2": "XK"}, {"id": "en:costa-rica", "name": "Kosta Ríka", "country_code_2": "CR"}, {"id": "en:croatia", "name": "Króatía", "country_code_2": "HR"}, {"id": "en:kiribati", "name": "Kíribatí", "country_code_2": "KI"}, {"id": "en:cocos-keeling-islands", "name": "Kókoseyjar", "country_code_2": "CC"}, {"id": "en:colombia", "name": "Kólumbía", "country_code_2": "CO"}, {"id": "en:comoros", "name": "Kómoreyjar", "country_code_2": "KM"}, {"id": "en:cuba", "name": "Kúba", "country_code_2": "CU"}, {"id": "en:kuwait", "name": "Kúveit", "country_code_2": "KW"}, {"id": "en:cyprus", "name": "Kýpur", "country_code_2": "CY"}, {"id": "en:laos", "name": "Laos", "country_code_2": "LA"}, {"id": "en:lesotho", "name": "Lesótó", "country_code_2": "LS"}, {"id": "en:latvia", "name": "Lettland", "country_code_2": "LV"}, {"id": "en:liechtenstein", "name": "Liechtenstein", "country_code_2": "LI"}, {"id": "en:lithuania", "name": "Litháen", "country_code_2": "LT"}, {"id": "en:lebanon", "name": "Líbanon", "country_code_2": "LB"}, {"id": "en:liberia", "name": "Líbería", "country_code_2": "LR"}, {"id": "en:libya", "name": "Líbýa", "country_code_2": "LY"}, {"id": "en:luxembourg", "name": "Lúxemborg", "country_code_2": "LU"}, {"id": "en:taiwan", "name": "Lýðveldið Kína", "country_code_2": "TW"}, {"id": "en:madagascar", "name": "Madagaskar", "country_code_2": "MG"}, {"id": "en:macau", "name": "Makaó", "country_code_2": "MO"}, {"id": "en:malaysia", "name": "Malasía", "country_code_2": "MY"}, {"id": "en:malawi", "name": "Malaví", "country_code_2": "MW"}, {"id": "en:maldives", "name": "Maldíveyjar", "country_code_2": "MV"}, {"id": "en:malta", "name": "Malta", "country_code_2": "MT"}, {"id": "en:mali", "name": "Malí", "country_code_2": "ML"}, {"id": "en:morocco", "name": "Marokkó", "country_code_2": "MA"}, {"id": "en:marshall-islands", "name": "Marshalleyjar", "country_code_2": "MH"}, {"id": "en:martinique", "name": "Martinique", "country_code_2": "MQ"}, {"id": "en:mayotte", "name": "Mayotte", "country_code_2": "YT"}, {"id": "en:mexico", "name": "Mexíkó", "country_code_2": "MX"}, {"id": "en:central-african-republic", "name": "Mið-Afríkulýðveldið", "country_code_2": "CF"}, {"id": "en:equatorial-guinea", "name": "Miðbaugs-Gínea", "country_code_2": "GQ"}, {"id": "en:moldova", "name": "Moldóva", "country_code_2": "MD"}, {"id": "en:mongolia", "name": "Mongólía", "country_code_2": "MN"}, {"id": "en:montserrat", "name": "Montserrat", "country_code_2": "MS"}, {"id": "en:mauritania", "name": "Máritanía", "country_code_2": "MR"}, {"id": "en:mauritius", "name": "Máritíus", "country_code_2": "MU"}, {"id": "en:federated-states-of-micronesia", "name": "Míkrónesía", "country_code_2": "FM"}, {"id": "en:monaco", "name": "Mónakó", "country_code_2": "MC"}, {"id": "en:mozambique", "name": "Mósambík", "country_code_2": "MZ"}, {"id": "en:isle-of-man", "name": "Mön", "country_code_2": "IM"}, {"id": "en:namibia", "name": "Namibía", "country_code_2": "NA"}, {"id": "en:nepal", "name": "Nepal", "country_code_2": "NP"}, {"id": "en:niue", "name": "Niue", "country_code_2": "NU"}, {"id": "en:norway", "name": "Noregur", "country_code_2": "NO"}, {"id": "en:norfolk-island", "name": "Norfolkeyja", "country_code_2": "NF"}, {"id": "en:north-korea", "name": "Norður-Kórea", "country_code_2": "KP"}, {"id": "en:north-macedonia", "name": "Norður-Makedónía", "country_code_2": "MK"}, {"id": "en:northern-mariana-islands", "name": "Norður-Maríanaeyjar", "country_code_2": "MP"}, {"id": "en:nauru", "name": "Nárú", "country_code_2": "NR"}, {"id": "en:niger", "name": "Níger", "country_code_2": "NE"}, {"id": "en:nigeria", "name": "Nígería", "country_code_2": "NG"}, {"id": "en:nicaragua", "name": "Níkaragva", "country_code_2": "NI"}, {"id": "en:new-caledonia", "name": "Nýja-Kaledónía", "country_code_2": "NC"}, {"id": "en:new-zealand", "name": "Nýja-Sjáland", "country_code_2": "NZ"}, {"id": "en:pakistan", "name": "Pakistan", "country_code_2": "PK"}, {"id": "en:state-of-palestine", "name": "Palestínuríki", "country_code_2": "PS"}, {"id": "en:palau", "name": "Palá", "country_code_2": "PW"}, {"id": "en:panama", "name": "Panama", "country_code_2": "PA"}, {"id": "en:papua-new-guinea", "name": "Papúa Nýja-Gínea", "country_code_2": "PG"}, {"id": "en:paraguay", "name": "Paragvæ", "country_code_2": "PY"}, {"id": "en:peru", "name": "Perú", "country_code_2": "PE"}, {"id": "en:pitcairn", "name": "Pitcairn", "country_code_2": "PN"}, {"id": "en:portugal", "name": "Portúgal", "country_code_2": "PT"}, {"id": "en:poland", "name": "Pólland", "country_code_2": "PL"}, {"id": "en:puerto-rico", "name": "Púertó Ríkó", "country_code_2": "PR"}, {"id": "en:reunion", "name": "Réunion", "country_code_2": "RE"}, {"id": "en:rwanda", "name": "Rúanda", "country_code_2": "RW"}, {"id": "en:romania", "name": "Rúmenía", "country_code_2": "RO"}, {"id": "en:russia", "name": "Rússland", "country_code_2": "RU"}, {"id": "en:saint-helena", "name": "Saint Helena", "country_code_2": "SH"}, {"id": "en:saint-martin", "name": "Saint Martin", "country_code_2": "MF"}, {"id": "en:saint-barthelemy", "name": "Saint-Barthélemy", "country_code_2": "BL"}, {"id": "en:solomon-islands", "name": "Salómonseyjar", "country_code_2": "SB"}, {"id": "en:zambia", "name": "Sambía", "country_code_2": "ZM"}, {"id": "en:united-arab-emirates", "name": "Sameinuðu arabísku furstadæmin", "country_code_2": "AE"}, {"id": "en:samoa", "name": "Samóa", "country_code_2": "WS"}, {"id": "en:san-marino", "name": "San Marínó", "country_code_2": "SM"}, {"id": "en:saint-kitts-and-nevis", "name": "Sankti Kristófer og Nevis", "country_code_2": "KN"}, {"id": "en:saint-lucia", "name": "Sankti Lúsía", "country_code_2": "LC"}, {"id": "en:saint-pierre-and-miquelon", "name": "Sankti Pierre og Miquelon", "country_code_2": "PM"}, {"id": "en:saint-vincent-and-the-grenadines", "name": "Sankti Vinsent og Grenadíneyjar", "country_code_2": "VC"}, {"id": "en:sao-tome-and-principe", "name": "Saó Tóme og Prinsípe", "country_code_2": "ST"}, {"id": "en:senegal", "name": "Senegal", "country_code_2": "SN"}, {"id": "en:serbia", "name": "Serbía", "country_code_2": "RS"}, {"id": "en:seychelles", "name": "Seychelles-eyjar", "country_code_2": "SC"}, {"id": "en:zimbabwe", "name": "Simbabve", "country_code_2": "ZW"}, {"id": "en:singapore", "name": "Singapúr", "country_code_2": "SG"}, {"id": "en:sint-maarten", "name": "Sint Maarten", "country_code_2": "SX"}, {"id": "en:slovakia", "name": "Slóvakía", "country_code_2": "SK"}, {"id": "en:slovenia", "name": "Slóvenía", "country_code_2": "SI"}, {"id": "en:united-states-minor-outlying-islands", "name": "Smáeyjar Bandaríkjanna", "country_code_2": "UM"}, {"id": "en:spain", "name": "Spánn", "country_code_2": "ES"}, {"id": "en:sri-lanka", "name": "Srí Lanka", "country_code_2": "LK"}, {"id": "en:south-africa", "name": "Suður-Afríka", "country_code_2": "ZA"}, {"id": "en:south-georgia-and-the-south-sandwich-islands", "name": "Suður-Georgía og Suður-Sandvíkureyjar", "country_code_2": "GS"}, {"id": "en:south-korea", "name": "Suður-Kórea", "country_code_2": "KR"}, {"id": "en:south-sudan", "name": "Suður-Súdan", "country_code_2": "SS"}, {"id": "en:svalbard-and-jan-mayen", "name": "Svalbard and Jan Mayen", "country_code_2": "SJ"}, {"id": "en:montenegro", "name": "Svartfjallaland", "country_code_2": "ME"}, {"id": "en:swaziland", "name": "Svasíland", "country_code_2": "SZ"}, {"id": "en:switzerland", "name": "Sviss", "country_code_2": "CH"}, {"id": "en:sweden", "name": "Svíþjóð", "country_code_2": "SE"}, {"id": "en:saudi-arabia", "name": "Sádí-Arabía", "country_code_2": "SA"}, {"id": "en:sierra-leone", "name": "Síerra Leóne", "country_code_2": "SL"}, {"id": "en:chile", "name": "Síle", "country_code_2": "CL"}, {"id": "en:somalia", "name": "Sómalía", "country_code_2": "SO"}, {"id": "en:sudan", "name": "Súdan", "country_code_2": "SD"}, {"id": "en:suriname", "name": "Súrínam", "country_code_2": "SR"}, {"id": "en:syria", "name": "Sýrland", "country_code_2": "SY"}, {"id": "en:tajikistan", "name": "Tadsjikistan", "country_code_2": "TJ"}, {"id": "en:tanzania", "name": "Tansanía", "country_code_2": "TZ"}, {"id": "en:thailand", "name": "Taíland", "country_code_2": "TH"}, {"id": "en:tonga", "name": "Tonga", "country_code_2": "TO"}, {"id": "en:trinidad-and-tobago", "name": "Trínidad og Tóbagó", "country_code_2": "TT"}, {"id": "en:chad", "name": "Tsjad", "country_code_2": "TD"}, {"id": "en:turks-and-caicos-islands", "name": "Turks- og Caicoseyjar", "country_code_2": "TC"}, {"id": "en:turkey", "name": "Tyrkland", "country_code_2": "TR"}, {"id": "en:czech-republic", "name": "Tékkland", "country_code_2": "CZ"}, {"id": "en:togo", "name": "Tógó", "country_code_2": "TG"}, {"id": "en:tokelau", "name": "Tókelá", "country_code_2": "TK"}, {"id": "en:tunisia", "name": "Túnis", "country_code_2": "TN"}, {"id": "en:turkmenistan", "name": "Túrkmenistan", "country_code_2": "TM"}, {"id": "en:tuvalu", "name": "Túvalúeyjar", "country_code_2": "TV"}, {"id": "en:hungary", "name": "Ungverjaland", "country_code_2": "HU"}, {"id": "en:vanuatu", "name": "Vanúatú", "country_code_2": "VU"}, {"id": "en:vatican-city", "name": "Vatíkanið", "country_code_2": "VA"}, {"id": "en:venezuela", "name": "Venesúela", "country_code_2": "VE"}, {"id": "en:republic-of-the-congo", "name": "Vestur-Kongó", "country_code_2": "CG"}, {"id": "en:western-sahara", "name": "Vestur-Sahara", "country_code_2": "EH"}, {"id": "en:vietnam", "name": "Víetnam", "country_code_2": "VN"}, {"id": "en:wallis-and-futuna", "name": "Wallis- og Fútúnaeyjar", "country_code_2": "WF"}, {"id": "en:world", "name": "World", "country_code_2": "world"}, {"id": "en:aland-islands", "name": "Álandseyjar", "country_code_2": "AX"}, {"id": "en:australia", "name": "Ástralía", "country_code_2": "AU"}, {"id": "en:iraq", "name": "Írak", "country_code_2": "IQ"}, {"id": "en:iran", "name": "Íran", "country_code_2": "IR"}, {"id": "en:ireland", "name": "Írska lýðveldið", "country_code_2": "IE"}, {"id": "en:iceland", "name": "Ísland", "country_code_2": "IS"}, {"id": "en:israel", "name": "Ísrael", "country_code_2": "IL"}, {"id": "en:italy", "name": "Ítalía", "country_code_2": "IT"}, {"id": "en:oman", "name": "Óman", "country_code_2": "OM"}, {"id": "en:uganda", "name": "Úganda", "country_code_2": "UG"}, {"id": "en:ukraine", "name": "Úkraína", "country_code_2": "UA"}, {"id": "en:uruguay", "name": "Úrúgvæ", "country_code_2": "UY"}, {"id": "en:uzbekistan", "name": "Úsbekistan", "country_code_2": "UZ"}, {"id": "en:germany", "name": "Þýskaland", "country_code_2": "DE"}]