[{"id": "en:american-samoa", "name": "American Samoa", "country_code_2": "AS"}, {"id": "en:anguilla", "name": "Anguilla", "country_code_2": "AI"}, {"id": "en:antarctic", "name": "Antarctic", "country_code_2": "AQ"}, {"id": "en:bouvet-island", "name": "Bouvet Island", "country_code_2": "BV"}, {"id": "en:british-indian-ocean-territory", "name": "British Indian Ocean Territory", "country_code_2": "IO"}, {"id": "en:british-virgin-islands", "name": "British Virgin Islands", "country_code_2": "VG"}, {"id": "en:caribbean-netherlands", "name": "Caribbean Netherlands", "country_code_2": "BQ"}, {"id": "en:cayman-islands", "name": "Cayman Islands", "country_code_2": "KY"}, {"id": "en:christmas-island", "name": "Christmas Island", "country_code_2": "CX"}, {"id": "en:cocos-keeling-islands", "name": "Cocos (Keeling) Islands", "country_code_2": "CC"}, {"id": "en:cook-islands", "name": "Cook Islands", "country_code_2": "CK"}, {"id": "en:curacao", "name": "Curaçao", "country_code_2": "CW"}, {"id": "en:democratic-republic-of-the-congo", "name": "Democratic Republic of the Congo", "country_code_2": "CD"}, {"id": "en:dominica", "name": "Dominica", "country_code_2": "DM"}, {"id": "en:el-salvador", "name": "El Salvador", "country_code_2": "SV"}, {"id": "en:equatorial-guinea", "name": "Equatorial Guinea", "country_code_2": "GQ"}, {"id": "en:falkland-islands", "name": "Falkland Islands", "country_code_2": "FK"}, {"id": "en:faroe-islands", "name": "Faroe Islands", "country_code_2": "FO"}, {"id": "en:federated-states-of-micronesia", "name": "Federated States of Micronesia", "country_code_2": "FM"}, {"id": "en:french-guiana", "name": "French Guiana", "country_code_2": "GF"}, {"id": "en:french-polynesia", "name": "French Polynesia", "country_code_2": "PF"}, {"id": "en:french-southern-and-antarctic-lands", "name": "French Southern and Antarctic Lands", "country_code_2": "TF"}, {"id": "en:gibraltar", "name": "Gibraltar", "country_code_2": "GI"}, {"id": "en:grenada", "name": "Grenada", "country_code_2": "GD"}, {"id": "en:guadeloupe", "name": "Guadeloupe", "country_code_2": "GP"}, {"id": "en:guam", "name": "Guam", "country_code_2": "GU"}, {"id": "en:guatemala", "name": "Guatemala", "country_code_2": "GT"}, {"id": "en:guernsey", "name": "Guernsey", "country_code_2": "GG"}, {"id": "en:guinea", "name": "Guinea", "country_code_2": "GN"}, {"id": "en:guinea-bissau", "name": "Guinea-Bissau", "country_code_2": "GW"}, {"id": "en:haiti", "name": "Haiti", "country_code_2": "HT"}, {"id": "en:heard-island-and-mcdonald-islands", "name": "Heard Island and McDonald Islands", "country_code_2": "HM"}, {"id": "en:isle-of-man", "name": "Isle of Man", "country_code_2": "IM"}, {"id": "en:kosovo", "name": "Kosovo", "country_code_2": "XK"}, {"id": "en:lesotho", "name": "Lesotho", "country_code_2": "LS"}, {"id": "en:liberia", "name": "Liberia", "country_code_2": "LR"}, {"id": "en:liechtenstein", "name": "Liechtenstein", "country_code_2": "LI"}, {"id": "en:luxembourg", "name": "Luxembourg", "country_code_2": "LU"}, {"id": "en:malawi", "name": "Malawi", "country_code_2": "MW"}, {"id": "en:mali", "name": "Mali", "country_code_2": "ML"}, {"id": "en:malta", "name": "Malta", "country_code_2": "MT"}, {"id": "en:marshall-islands", "name": "Marshall Islands", "country_code_2": "MH"}, {"id": "en:martinique", "name": "Martinique", "country_code_2": "MQ"}, {"id": "en:mayotte", "name": "Mayotte", "country_code_2": "YT"}, {"id": "en:monaco", "name": "Monaco", "country_code_2": "MC"}, {"id": "en:montenegro", "name": "Montenegro", "country_code_2": "ME"}, {"id": "en:montserrat", "name": "Montserrat", "country_code_2": "MS"}, {"id": "en:mozambique", "name": "Mozambique", "country_code_2": "MZ"}, {"id": "en:nauru", "name": "Nauru", "country_code_2": "NR"}, {"id": "en:new-caledonia", "name": "New Caledonia", "country_code_2": "NC"}, {"id": "en:nicaragua", "name": "Nicaragua", "country_code_2": "NI"}, {"id": "en:niue", "name": "Niue", "country_code_2": "NU"}, {"id": "en:norfolk-island", "name": "Norfolk Island", "country_code_2": "NF"}, {"id": "en:northern-mariana-islands", "name": "Northern Mariana Islands", "country_code_2": "MP"}, {"id": "en:palau", "name": "Palau", "country_code_2": "PW"}, {"id": "en:papua-new-guinea", "name": "Papua New Guinea", "country_code_2": "PG"}, {"id": "en:paraguay", "name": "Paraguay", "country_code_2": "PY"}, {"id": "en:reunion", "name": "Réunion", "country_code_2": "RE"}, {"id": "en:saint-helena", "name": "Saint Helena", "country_code_2": "SH"}, {"id": "en:saint-kitts-and-nevis", "name": "Saint Kitts and Nevis", "country_code_2": "KN"}, {"id": "en:saint-lucia", "name": "Saint Lucia", "country_code_2": "LC"}, {"id": "en:saint-martin", "name": "Saint Martin", "country_code_2": "MF"}, {"id": "en:saint-pierre-and-miquelon", "name": "Saint Pierre and Miquelon", "country_code_2": "PM"}, {"id": "en:saint-vincent-and-the-grenadines", "name": "Saint Vincent and the Grenadines", "country_code_2": "VC"}, {"id": "en:saint-barthelemy", "name": "Saint-Barthélemy", "country_code_2": "BL"}, {"id": "en:san-marino", "name": "San Marino", "country_code_2": "SM"}, {"id": "en:sao-tome-and-principe", "name": "Sao Tomé and Príncipe", "country_code_2": "ST"}, {"id": "en:seychelles", "name": "Seychelles", "country_code_2": "SC"}, {"id": "en:sierra-leone", "name": "Sierra Leone", "country_code_2": "SL"}, {"id": "en:sint-maarten", "name": "Sint Maarten", "country_code_2": "SX"}, {"id": "en:slovakia", "name": "Slovakia", "country_code_2": "SK"}, {"id": "en:south-georgia-and-the-south-sandwich-islands", "name": "South Georgia and the South Sandwich Islands", "country_code_2": "GS"}, {"id": "en:state-of-palestine", "name": "State of Palestine", "country_code_2": "PS"}, {"id": "en:svalbard-and-jan-mayen", "name": "Svalbard and Jan Mayen", "country_code_2": "SJ"}, {"id": "en:swaziland", "name": "Swaziland", "country_code_2": "SZ"}, {"id": "en:togo", "name": "Togo", "country_code_2": "TG"}, {"id": "en:tokelau", "name": "Tokelau", "country_code_2": "TK"}, {"id": "en:tonga", "name": "Tonga", "country_code_2": "TO"}, {"id": "en:turks-and-caicos-islands", "name": "Turks and Caicos Islands", "country_code_2": "TC"}, {"id": "en:tuvalu", "name": "Tuvalu", "country_code_2": "TV"}, {"id": "en:united-states-minor-outlying-islands", "name": "United States Minor Outlying Islands", "country_code_2": "UM"}, {"id": "en:uruguay", "name": "Uruguay", "country_code_2": "UY"}, {"id": "en:venezuela", "name": "Venezuela", "country_code_2": "VE"}, {"id": "en:virgin-islands-of-the-united-states", "name": "Virgin Islands of the United States", "country_code_2": "VI"}, {"id": "en:wallis-and-futuna", "name": "Wallis and Futuna", "country_code_2": "WF"}, {"id": "en:western-sahara", "name": "Western Sahara", "country_code_2": "EH"}, {"id": "en:yugoslavia", "name": "Yugoslavia", "country_code_2": "YU"}, {"id": "en:aland-islands", "name": "Åland Islands", "country_code_2": "AX"}, {"id": "en:angola", "name": "అంగోలా", "country_code_2": "AO"}, {"id": "en:andorra", "name": "అండొర్రా", "country_code_2": "AD"}, {"id": "en:azerbaijan", "name": "అజర్‌బైజాన్", "country_code_2": "AZ"}, {"id": "en:united-states", "name": "అమెరికా సంయుక్త రాష్ట్రాలు", "country_code_2": "US"}, {"id": "en:aruba", "name": "అరుబా", "country_code_2": "AW"}, {"id": "en:argentina", "name": "అర్జెంటీనా", "country_code_2": "AR"}, {"id": "en:algeria", "name": "అల్జీరియా", "country_code_2": "DZ"}, {"id": "en:albania", "name": "అల్బేనియా", "country_code_2": "AL"}, {"id": "en:antigua-and-barbuda", "name": "ఆంటిగ్వా మరియు బార్బుడా", "country_code_2": "AG"}, {"id": "en:afghanistan", "name": "ఆఫ్ఘనిస్తాన్", "country_code_2": "AF"}, {"id": "en:armenia", "name": "ఆర్మేనియా", "country_code_2": "AM"}, {"id": "en:austria", "name": "ఆస్ట్రియా", "country_code_2": "AT"}, {"id": "en:australia", "name": "ఆస్ట్రేలియా", "country_code_2": "AU"}, {"id": "en:indonesia", "name": "ఇండోనేషియా", "country_code_2": "ID"}, {"id": "en:israel", "name": "ఇజ్రాయిల్", "country_code_2": "IL"}, {"id": "en:italy", "name": "ఇటలీ", "country_code_2": "IT"}, {"id": "en:ethiopia", "name": "ఇథియోపియా", "country_code_2": "ET"}, {"id": "en:iraq", "name": "ఇరాక్", "country_code_2": "IQ"}, {"id": "en:iran", "name": "ఇరాన్", "country_code_2": "IR"}, {"id": "en:ecuador", "name": "ఈక్వడార్", "country_code_2": "EC"}, {"id": "en:egypt", "name": "ఈజిప్టు", "country_code_2": "EG"}, {"id": "en:ukraine", "name": "ఉక్రెయిన్", "country_code_2": "UA"}, {"id": "en:uganda", "name": "ఉగాండా", "country_code_2": "UG"}, {"id": "en:uzbekistan", "name": "ఉజ్బెకిస్తాన్", "country_code_2": "UZ"}, {"id": "en:north-korea", "name": "ఉత్తర కొరియా", "country_code_2": "KP"}, {"id": "en:north-macedonia", "name": "ఉత్తర మెసిడోనియా", "country_code_2": "MK"}, {"id": "en:eritrea", "name": "ఎరిట్రియా", "country_code_2": "ER"}, {"id": "en:estonia", "name": "ఎస్టోనియా", "country_code_2": "EE"}, {"id": "en:iceland", "name": "ఐస్‌లాండ్", "country_code_2": "IS"}, {"id": "en:oman", "name": "ఒమన్", "country_code_2": "OM"}, {"id": "en:cambodia", "name": "కంబోడియా", "country_code_2": "KH"}, {"id": "en:kazakhstan", "name": "కజకస్తాన్", "country_code_2": "KZ"}, {"id": "en:qatar", "name": "కతర్", "country_code_2": "QA"}, {"id": "en:republic-of-the-congo", "name": "కాంగో రిపబ్లిక్", "country_code_2": "CG"}, {"id": "en:cameroon", "name": "కామెరూన్", "country_code_2": "CM"}, {"id": "en:kiribati", "name": "కిరిబాతి", "country_code_2": "KI"}, {"id": "en:kyrgyzstan", "name": "కిర్గిజిస్తాన్", "country_code_2": "KG"}, {"id": "en:kuwait", "name": "కువైట్", "country_code_2": "KW"}, {"id": "en:canada", "name": "కెనడా", "country_code_2": "CA"}, {"id": "en:kenya", "name": "కెన్యా", "country_code_2": "KE"}, {"id": "en:cape-verde", "name": "కేప్ వర్దె", "country_code_2": "CV"}, {"id": "en:comoros", "name": "కొమొరోస్", "country_code_2": "KM"}, {"id": "en:colombia", "name": "కొలంబియా", "country_code_2": "CO"}, {"id": "en:cote-d-ivoire", "name": "కోటె డి ఐవొరి", "country_code_2": "CI"}, {"id": "en:costa-rica", "name": "కోస్టారీకా", "country_code_2": "CR"}, {"id": "en:cuba", "name": "క్యూబా", "country_code_2": "CU"}, {"id": "en:croatia", "name": "క్రొయేషియా", "country_code_2": "HR"}, {"id": "en:gabon", "name": "గబాన్", "country_code_2": "GA"}, {"id": "en:guyana", "name": "గయానా", "country_code_2": "GY"}, {"id": "en:gambia", "name": "గాంబియా", "country_code_2": "GM"}, {"id": "en:greenland", "name": "గ్రీన్‌లాండ్", "country_code_2": "GL"}, {"id": "en:greece", "name": "గ్రీస్", "country_code_2": "GR"}, {"id": "en:ghana", "name": "ఘనా", "country_code_2": "GH"}, {"id": "en:chad", "name": "చాద్", "country_code_2": "TD"}, {"id": "en:chile", "name": "చిలీ", "country_code_2": "CL"}, {"id": "en:czech-republic", "name": "చెక్ రిపబ్లిక్", "country_code_2": "CZ"}, {"id": "en:china", "name": "చైనా", "country_code_2": "CN"}, {"id": "en:japan", "name": "జపాన్", "country_code_2": "JP"}, {"id": "en:jamaica", "name": "జమైకా", "country_code_2": "JM"}, {"id": "en:germany", "name": "జర్మనీ", "country_code_2": "DE"}, {"id": "en:zambia", "name": "జాంబియా", "country_code_2": "ZM"}, {"id": "en:georgia", "name": "జార్జియా", "country_code_2": "GE"}, {"id": "en:zimbabwe", "name": "జింబాబ్వే", "country_code_2": "ZW"}, {"id": "en:djibouti", "name": "జిబౌటి", "country_code_2": "DJ"}, {"id": "en:jersey", "name": "జెర్సీ", "country_code_2": "JE"}, {"id": "en:jordan", "name": "జోర్డాన్", "country_code_2": "JO"}, {"id": "en:turkey", "name": "టర్కీ", "country_code_2": "TR"}, {"id": "en:tanzania", "name": "టాంజానియా", "country_code_2": "TZ"}, {"id": "en:tunisia", "name": "ట్యునీషియా", "country_code_2": "TN"}, {"id": "en:trinidad-and-tobago", "name": "ట్రినిడాడ్ మరియు టొబాగో", "country_code_2": "TT"}, {"id": "en:denmark", "name": "డెన్మార్క్", "country_code_2": "DK"}, {"id": "en:dominican-republic", "name": "డొమెనికన్ రిపబ్లిక్", "country_code_2": "DO"}, {"id": "en:tajikistan", "name": "తజికిస్తాన్", "country_code_2": "TJ"}, {"id": "en:turkmenistan", "name": "తుర్కమేనిస్తాన్", "country_code_2": "TM"}, {"id": "en:timor-leste", "name": "తూర్పు తైమూర్", "country_code_2": "TL"}, {"id": "en:taiwan", "name": "తైవాన్", "country_code_2": "TW"}, {"id": "en:thailand", "name": "థాయిలాండ్", "country_code_2": "TH"}, {"id": "en:south-africa", "name": "దక్షిణ ఆఫ్రికా", "country_code_2": "ZA"}, {"id": "en:south-korea", "name": "దక్షిణ కొరియా", "country_code_2": "KR"}, {"id": "en:south-sudan", "name": "దక్షిణ సూడాన్", "country_code_2": "SS"}, {"id": "en:namibia", "name": "నమీబియా", "country_code_2": "NA"}, {"id": "en:norway", "name": "నార్వే", "country_code_2": "NO"}, {"id": "en:netherlands", "name": "నెదర్లాండ్", "country_code_2": "NL"}, {"id": "en:nepal", "name": "నేపాల్", "country_code_2": "NP"}, {"id": "en:niger", "name": "నైజర్", "country_code_2": "NE"}, {"id": "en:nigeria", "name": "నైజీరియా", "country_code_2": "NG"}, {"id": "en:new-zealand", "name": "న్యూజీలాండ్", "country_code_2": "NZ"}, {"id": "en:panama", "name": "పనామా", "country_code_2": "PA"}, {"id": "en:pakistan", "name": "పాకిస్తాన్", "country_code_2": "PK"}, {"id": "en:pitcairn", "name": "పిట్ కెయిర్న్ దీవులు", "country_code_2": "PN"}, {"id": "en:peru", "name": "పెరూ", "country_code_2": "PE"}, {"id": "en:portugal", "name": "పోర్చుగల్", "country_code_2": "PT"}, {"id": "en:poland", "name": "పోలాండ్", "country_code_2": "PL"}, {"id": "en:world", "name": "ప్రపంచము", "country_code_2": "world"}, {"id": "en:fiji", "name": "ఫిజీ", "country_code_2": "FJ"}, {"id": "en:finland", "name": "ఫిన్ లాండ్", "country_code_2": "FI"}, {"id": "en:philippines", "name": "ఫిలిప్పీన్స్", "country_code_2": "PH"}, {"id": "en:puerto-rico", "name": "ఫ్యూర్టో రికో", "country_code_2": "PR"}, {"id": "en:france", "name": "ఫ్రాన్స్", "country_code_2": "FR"}, {"id": "en:bangladesh", "name": "బంగ్లాదేశ్", "country_code_2": "BD"}, {"id": "en:burkina-faso", "name": "బర్కీనా ఫాసో", "country_code_2": "BF"}, {"id": "en:bulgaria", "name": "బల్గేరియా", "country_code_2": "BG"}, {"id": "en:the-bahamas", "name": "బహామాస్", "country_code_2": "BS"}, {"id": "en:bahrain", "name": "బహ్రయిన్", "country_code_2": "BH"}, {"id": "en:barbados", "name": "బార్బడోస్", "country_code_2": "BB"}, {"id": "en:burundi", "name": "బురుండి", "country_code_2": "BI"}, {"id": "en:benin", "name": "బెనిన్", "country_code_2": "BJ"}, {"id": "en:bermuda", "name": "బెర్ముడా", "country_code_2": "BM"}, {"id": "en:belarus", "name": "బెలారస్", "country_code_2": "BY"}, {"id": "en:belize", "name": "బెలిజ్", "country_code_2": "BZ"}, {"id": "en:belgium", "name": "బెల్జియం", "country_code_2": "BE"}, {"id": "en:bolivia", "name": "బొలీవియా", "country_code_2": "BO"}, {"id": "en:botswana", "name": "బోత్సువానా", "country_code_2": "BW"}, {"id": "en:bosnia-and-herzegovina", "name": "బోస్నియా మరియు హెర్జెగొవీనా", "country_code_2": "BA"}, {"id": "en:brunei", "name": "బ్రూనై", "country_code_2": "BN"}, {"id": "en:brazil", "name": "బ్రెజిల్", "country_code_2": "BR"}, {"id": "en:india", "name": "భారత దేశము", "country_code_2": "IN"}, {"id": "en:bhutan", "name": "భూటాన్", "country_code_2": "BT"}, {"id": "en:mongolia", "name": "మంగోలియా", "country_code_2": "MN"}, {"id": "en:macau", "name": "మకావు", "country_code_2": "MO"}, {"id": "en:madagascar", "name": "మడగాస్కర్", "country_code_2": "MG"}, {"id": "en:myanmar", "name": "మయన్మార్", "country_code_2": "MM"}, {"id": "en:malaysia", "name": "మలేషియా", "country_code_2": "MY"}, {"id": "en:mauritius", "name": "మారిషస్", "country_code_2": "MU"}, {"id": "en:maldives", "name": "మాల్దీవులు", "country_code_2": "MV"}, {"id": "en:mexico", "name": "మెక్సికో", "country_code_2": "MX"}, {"id": "en:morocco", "name": "మొరాకో", "country_code_2": "MA"}, {"id": "en:moldova", "name": "మోల్డోవా", "country_code_2": "MD"}, {"id": "en:mauritania", "name": "మౌరిటానియ", "country_code_2": "MR"}, {"id": "en:united-arab-emirates", "name": "యునైటెడ్ అరబ్ ఎమిరేట్స్", "country_code_2": "AE"}, {"id": "en:united-kingdom", "name": "యునైటెడ్ కింగ్ డమ్", "country_code_2": "UK"}, {"id": "en:yemen", "name": "యెమన్", "country_code_2": "YE"}, {"id": "en:russia", "name": "రష్యా", "country_code_2": "RU"}, {"id": "en:ireland", "name": "రిపబ్లిక్ ఆఫ్ ఐర్లాండ్", "country_code_2": "IE"}, {"id": "en:rwanda", "name": "రువాండా", "country_code_2": "RW"}, {"id": "en:romania", "name": "రొమేనియా", "country_code_2": "RO"}, {"id": "en:latvia", "name": "లాట్వియా", "country_code_2": "LV"}, {"id": "en:laos", "name": "లావోస్", "country_code_2": "LA"}, {"id": "en:lithuania", "name": "లిథువేనియా", "country_code_2": "LT"}, {"id": "en:libya", "name": "లిబియా", "country_code_2": "LY"}, {"id": "en:lebanon", "name": "లెబనాన్", "country_code_2": "LB"}, {"id": "en:vanuatu", "name": "వనాటు", "country_code_2": "VU"}, {"id": "en:vatican-city", "name": "వాటికన్ నగరం", "country_code_2": "VA"}, {"id": "en:vietnam", "name": "వియత్నాం", "country_code_2": "VN"}, {"id": "en:sri-lanka", "name": "శ్రీలంక", "country_code_2": "LK"}, {"id": "en:samoa", "name": "సమోవా", "country_code_2": "WS"}, {"id": "en:singapore", "name": "సింగపూరు", "country_code_2": "SG"}, {"id": "en:syria", "name": "సిరియా", "country_code_2": "SY"}, {"id": "en:suriname", "name": "సురినామ్", "country_code_2": "SR"}, {"id": "en:sudan", "name": "సూడాన్", "country_code_2": "SD"}, {"id": "en:central-african-republic", "name": "సెంట్రల్ ఆఫ్రికన్ రిపబ్లిక్", "country_code_2": "CF"}, {"id": "en:senegal", "name": "సెనెగల్", "country_code_2": "SN"}, {"id": "en:serbia", "name": "సెర్బియా", "country_code_2": "RS"}, {"id": "en:cyprus", "name": "సైప్రస్", "country_code_2": "CY"}, {"id": "en:somalia", "name": "సొమాలియా", "country_code_2": "SO"}, {"id": "en:solomon-islands", "name": "సోలమన్ దీవులు", "country_code_2": "SB"}, {"id": "en:saudi-arabia", "name": "సౌదీ అరేబియా", "country_code_2": "SA"}, {"id": "en:spain", "name": "స్పెయిన్", "country_code_2": "ES"}, {"id": "en:slovenia", "name": "స్లోవేనియా", "country_code_2": "SI"}, {"id": "en:switzerland", "name": "స్విట్జర్లాండ్", "country_code_2": "CH"}, {"id": "en:sweden", "name": "స్వీడన్", "country_code_2": "SE"}, {"id": "en:hungary", "name": "హంగేరి", "country_code_2": "HU"}, {"id": "en:hong-kong", "name": "హాంగ్‌కాంగ్", "country_code_2": "HK"}, {"id": "en:honduras", "name": "హోండురాస్", "country_code_2": "HN"}]